build2docker/__init__.py
build2docker/__main__.py
build2docker/_version.py
build2docker/app.py
build2docker/docker.py
build2docker/engine.py
build2docker/semver.py
build2docker/utils.py
build2docker/buildpacks/__init__.py
build2docker/buildpacks/_r_base.py
build2docker/buildpacks/base.py
build2docker/buildpacks/build2docker-entrypoint
build2docker/buildpacks/docker.py
build2docker/buildpacks/python3-login
build2docker/buildpacks/r.py
build2docker/buildpacks/conda/__init__.py
build2docker/buildpacks/conda/activate-conda.sh
build2docker/buildpacks/conda/environment.py-2.7-linux-64.lock
build2docker/buildpacks/conda/environment.py-2.7.yml
build2docker/buildpacks/conda/environment.py-3.10-linux-64.lock
build2docker/buildpacks/conda/environment.py-3.10-linux-aarch64.lock
build2docker/buildpacks/conda/environment.py-3.10.yml
build2docker/buildpacks/conda/environment.py-3.11-linux-64.lock
build2docker/buildpacks/conda/environment.py-3.11-linux-aarch64.lock
build2docker/buildpacks/conda/environment.py-3.11.lock
build2docker/buildpacks/conda/environment.py-3.11.yml
build2docker/buildpacks/conda/environment.py-3.12-linux-64.lock
build2docker/buildpacks/conda/environment.py-3.12-linux-aarch64.lock
build2docker/buildpacks/conda/environment.py-3.12.yml
build2docker/buildpacks/conda/environment.py-3.5-linux-64.lock
build2docker/buildpacks/conda/environment.py-3.5.yml
build2docker/buildpacks/conda/environment.py-3.6-linux-64.lock
build2docker/buildpacks/conda/environment.py-3.6.yml
build2docker/buildpacks/conda/environment.py-3.7-linux-64.lock
build2docker/buildpacks/conda/environment.py-3.7-linux-aarch64.lock
build2docker/buildpacks/conda/environment.py-3.7.yml
build2docker/buildpacks/conda/environment.py-3.8-linux-64.lock
build2docker/buildpacks/conda/environment.py-3.8-linux-aarch64.lock
build2docker/buildpacks/conda/environment.py-3.8.yml
build2docker/buildpacks/conda/environment.py-3.9-linux-64.lock
build2docker/buildpacks/conda/environment.py-3.9-linux-aarch64.lock
jupyter_build2docker-2024.9.0.dist-info/LICENSE
jupyter_build2docker-2024.9.0.dist-info/METADATA
jupyter_build2docker-2024.9.0.dist-info/WHEEL
jupyter_build2docker-2024.9.0.dist-info/entry_points.txt
jupyter_build2docker-2024.9.0.dist-info/top_level.txt
jupyter_build2docker-2024.9.0.dist-info/RECORD
