Metadata-Version: 2.1
Name: jupyter-build2docker
Version: 2024.9.0
Summary: Build2docker: Turn code repositories into Jupyter enabled Docker Images
Home-page: https://build2docker.readthedocs.io/en/latest/
Author: Project Jupyter Contributors
Author-email: jupyter@googlegroups.com
License: BSD
Project-URL: Documentation, https://build2docker.readthedocs.io
Project-URL: Funding, https://jupyter.org/about
Project-URL: Source, https://github.com/khulnasoft/build2docker/
Project-URL: Tracker, https://github.com/khulnasoft/build2docker/issues
Keywords: reproducible science environments docker
Classifier: Environment :: Console
Classifier: Intended Audience :: Developers
Classifier: Intended Audience :: System Administrators
Classifier: Intended Audience :: Science/Research
Classifier: License :: OSI Approved :: BSD License
Classifier: Programming Language :: Python
Classifier: Programming Language :: Python :: 3
Requires-Python: >=3.6
License-File: LICENSE
Requires-Dist: chardet
Requires-Dist: docker !=5.0.0
Requires-Dist: entrypoints
Requires-Dist: escapism
Requires-Dist: iso8601
Requires-Dist: jinja2
Requires-Dist: python-json-logger
Requires-Dist: requests
Requires-Dist: ruamel.yaml >=0.15
Requires-Dist: semver
Requires-Dist: toml
Requires-Dist: traitlets
